{"framework":"apd-framework-9.0.8","title":"Pomoć za Knjigu fontova","build_id":"556a936b094622a20257cf08","icon":"..\/GlobalArt\/AppIconDefault_FontBook.png","sections":{},"birdseed_version":4,"toc":["fntbcc65037b","fntbk1000","fntbk1003","fb34860","fntbk1001","fntb2bcb512d"],"locale":"hr","version":"10.11","enable_tracking":false,"source_schema":"apd-schema","platform":"mac","build_date":"2015.05.30-22:10:24","landing":"fntbede246a6","product":"fontbook","urls":{},"copyright":"","topics":{"fb34860":{"name":"Izrada kolekcija i medijateka","href":"fb34860.html","unavailable":true},"fntbk1014":{"searchName":"Eksportiranje fontova iz Knjige fontova","unavailable":true,"name":"Eksportiranje fontova iz Knjige fontova","href":"fntbk1014.html"},"fntbk1004":{"name":"Postavke Knjige fontova","href":"fntbk1004.html","unavailable":true},"fntbk1000":{"name":"Instaliranje i pregledavanje fontova","href":"fntbk1000.html","unavailable":true},"fntbede246a6":{"icon":"..\/GlobalArt\/AppLanding_FontBook.png","categories":["landing"],"name":"Pomoć za Knjigu fontova","href":"fntbede246a6.html"},"fntbcc65037b":{"name":"Pregled Knjige fontova","href":"fntbcc65037b.html","unavailable":true},"fntbk1003":{"searchName":"Provjera valjanosti fontova u Knjizi fontova","unavailable":true,"name":"Provjera valjanosti fontova","href":"fntbk1003.html"},"fntbk1001":{"searchName":"Ispis fontova u Knjizi fontova","unavailable":true,"name":"Ispis fontova","href":"fntbk1001.html"},"fb34862":{"name":"Vraćanje standardnih fontova","href":"fb34862.html","unavailable":true},"fntb2bcb512d":{"name":"Uklanjanje ili onemogućavanje fontova","href":"fntb2bcb512d.html","unavailable":true}},"copyright_text":"© 2015. Apple Inc. Sva prava pridržana.","css":""}